cf_signer/__init__.py
cf_signer/cf_signer.py
cf_signer/cli.py
cf_signer/utils.py
cf_signer-0.0.3.dist-info/AUTHORS.rst
cf_signer-0.0.3.dist-info/LICENSE
cf_signer-0.0.3.dist-info/METADATA
cf_signer-0.0.3.dist-info/WHEEL
cf_signer-0.0.3.dist-info/entry_points.txt
cf_signer-0.0.3.dist-info/top_level.txt
cf_signer-0.0.3.dist-info/RECORD
