Metadata-Version: 2.1
Name: cf-signer
Version: 0.0.3
Summary: Tool for Signing and Verifying Signatures of CloudFormation Templates
Home-page: https://github.com/avishayil/cf-signer
Author: Avishay Bar
Author-email: avishay.il@gmail.com
License: MIT license
Keywords: cf_signer
Platform: UNKNOWN
Classifier: Development Status :: 2 - Pre-Alpha
Classifier: Intended Audience :: Developers
Classifier: License :: OSI Approved :: MIT License
Classifier: Natural Language :: English
Classifier: Programming Language :: Python :: 3
Classifier: Programming Language :: Python :: 3.6
Classifier: Programming Language :: Python :: 3.7
Classifier: Programming Language :: Python :: 3.8
Requires-Python: >=3.6
License-File: LICENSE
License-File: AUTHORS.rst
Requires-Dist: Click (>=7.0)
Requires-Dist: PyOpenSSL (>=20.0.1)
Provides-Extra: develop
Requires-Dist: pytest (>=3) ; extra == 'develop'
Requires-Dist: flake8 (>=3.7.8) ; extra == 'develop'
Requires-Dist: pylint (>=2.8.3) ; extra == 'develop'
